gpu_control.cp310-win_amd64.pyd
gpu_control-1.0.0.dist-info/METADATA
gpu_control-1.0.0.dist-info/WHEEL
gpu_control-1.0.0.dist-info/top_level.txt
gpu_control-1.0.0.dist-info/RECORD
