Metadata-Version: 2.1
Name: gpu-control
Version: 1.0.0
Summary: NVIDIA GPU temp and fan control
Home-page: https://github.com/d0nk3yhm/gpu_controller
Author: Hans
Author-email: no.mail@example.com
License: UNKNOWN
Platform: UNKNOWN
Requires-Dist: numpy
